ufwio/__init__.py
ufwio/blob_pb2.py
ufwio/io.py
ufwio/lmdb_info.py
ufwio-0.0.2.dist-info/METADATA
ufwio-0.0.2.dist-info/WHEEL
ufwio-0.0.2.dist-info/top_level.txt
ufwio-0.0.2.dist-info/RECORD
