Metadata-Version: 2.1
Name: ufwio
Version: 0.0.2
Summary: A package for LMDB database operations
Home-page: https://github.com/pypa/sampleproject
Author: Wangyang.zuo
Author-email: wangyang.zuo@sophon.com
Classifier: Programming Language :: Python :: 3
Classifier: License :: OSI Approved :: MIT License
Classifier: Operating System :: OS Independent
Requires-Dist: numpy
Requires-Dist: lmdb
Requires-Dist: scipy
Requires-Dist: scikit-image
Requires-Dist: google
Requires-Dist: protobuf (==3.19.0)
